{
  "type": "Feature",
  "properties": {
    "gn:admin1_code":"01",
    "gn:asciiname":"Saint Patrick's",
    "gn:cc2":"MS",
    "gn:country_code":"MS",
    "gn:dem":103,
    "gn:feature_class":"P",
    "gn:feature_code":"PPL",
    "gn:name":"Saint Patrick's",
    "gn:population":0,
    "gn:timezone":"America/Montserrat",
    "iso:country":"MS",
    "name:und_x_variant":[
        "Saint Patrick's Village"
    ],
    "wof:name":"Saint Patrick's",
    "wof:placetype":"locality"
},
  "geometry": {"coordinates":[-62.19764,16.68808],"type":"Point"}
}