{
  "type": "Feature",
  "properties": {
    "gn:admin1_code":"03",
    "gn:asciiname":"Frith",
    "gn:country_code":"MS",
    "gn:dem":116,
    "gn:feature_class":"P",
    "gn:feature_code":"PPL",
    "gn:name":"Frith",
    "gn:population":0,
    "gn:timezone":"America/Montserrat",
    "iso:country":"MS",
    "wof:name":"Frith",
    "wof:placetype":"locality"
},
  "geometry": {"coordinates":[-62.21798,16.7448],"type":"Point"}
}